LICENSE
superinactive/__init__.py
superinactive/superinactive.py
superinactive/touch_file.py
superinactive-0.1.0.dist-info/entry_points.txt
superinactive-0.1.0.dist-info/LICENSE
superinactive-0.1.0.dist-info/WHEEL
superinactive-0.1.0.dist-info/METADATA
superinactive-0.1.0.dist-info/RECORD
