Metadata-Version: 2.1
Name: superinactive
Version: 0.1.0
Summary: 
Home-page: https://github.com/Inqbus/superinactive.git
License: MIT
Keywords: supervisor,supervisord,activity
Author: volker
Author-email: volker.jaenisch@inqbus.de
Requires-Python: >=3.7,<4.0
Classifier: Environment :: Console
Classifier: Framework :: supervisor
Classifier: License :: OSI Approved :: MIT License
Classifier: Operating System :: OS Independent
Classifier: Programming Language :: Python :: 3
Classifier: Programming Language :: Python :: 3.7
Classifier: Programming Language :: Python :: 3.8
Classifier: Programming Language :: Python :: 3.9
Classifier: Topic :: Software Development :: Libraries :: Python Modules
Requires-Dist: supervisor (>=4.2.1,<5.0.0)
Project-URL: Repository, https://github.com/Inqbus/superinactive.git
